jupyterlab_nasadaily/__init__.py
jupyterlab_nasadaily/_version.py
jupyterlab_nasadaily-1.0.1.data/data/share/jupyter/labextensions/jupyterlab_nasadaily/package.json
jupyterlab_nasadaily-1.0.1.data/data/share/jupyter/labextensions/jupyterlab_nasadaily/schemas/jupyterlab_nasadaily/package.json.orig
jupyterlab_nasadaily-1.0.1.data/data/share/jupyter/labextensions/jupyterlab_nasadaily/schemas/jupyterlab_nasadaily/plugin.json
jupyterlab_nasadaily-1.0.1.data/data/share/jupyter/labextensions/jupyterlab_nasadaily/static/509.3b9825cb622c2eccebec.js
jupyterlab_nasadaily-1.0.1.data/data/share/jupyter/labextensions/jupyterlab_nasadaily/static/728.5c74236b240ca8701bec.js
jupyterlab_nasadaily-1.0.1.data/data/share/jupyter/labextensions/jupyterlab_nasadaily/static/remoteEntry.a989074e747462b5e6ef.js
jupyterlab_nasadaily-1.0.1.data/data/share/jupyter/labextensions/jupyterlab_nasadaily/static/style.js
jupyterlab_nasadaily-1.0.1.data/data/share/jupyter/labextensions/jupyterlab_nasadaily/static/third-party-licenses.json
jupyterlab_nasadaily-1.0.1.data/data/share/jupyter/labextensions/jupyterlab_nasadaily/install.json
jupyterlab_nasadaily-1.0.1.dist-info/METADATA
jupyterlab_nasadaily-1.0.1.dist-info/WHEEL
jupyterlab_nasadaily-1.0.1.dist-info/licenses/LICENSE
jupyterlab_nasadaily-1.0.1.dist-info/RECORD
