Metadata-Version: 2.3
Name: jupyterlab_nasadaily
Version: 1.0.1
Summary: JupyterLab Extension to Show Astronomy Picture of the Day from NASA
Project-URL: Homepage, https://github.com/firezym/jupyterlab_nasadaily
Project-URL: Bug Tracker, https://github.com/firezym/jupyterlab_nasadaily/issues
Project-URL: Repository, https://github.com/firezym/jupyterlab_nasadaily.git
Author-email: ocean <firezym@gmail.com>
License: BSD 3-Clause License
Keywords: jupyter,jupyterlab,jupyterlab-extension
Classifier: Framework :: Jupyter
Classifier: Framework :: Jupyter :: JupyterLab
Classifier: Framework :: Jupyter :: JupyterLab :: 4
Classifier: Framework :: Jupyter :: JupyterLab :: Extensions
Classifier: Framework :: Jupyter :: JupyterLab :: Extensions :: Prebuilt
Classifier: License :: OSI Approved :: BSD License
Classifier: Programming Language :: Python
Classifier: Programming Language :: Python :: 3
Classifier: Programming Language :: Python :: 3.8
Classifier: Programming Language :: Python :: 3.9
Classifier: Programming Language :: Python :: 3.10
Classifier: Programming Language :: Python :: 3.11
Classifier: Programming Language :: Python :: 3.12
Requires-Python: >=3.8
